codeUtils/__init__.py
codeUtils/decorator/__init__.py
codeUtils/decorator/exec_time.py
codeUtils/tools/__init__.py
codeElfin-0.0.2.dist-info/LICENSE
codeElfin-0.0.2.dist-info/METADATA
codeElfin-0.0.2.dist-info/WHEEL
codeElfin-0.0.2.dist-info/top_level.txt
codeElfin-0.0.2.dist-info/RECORD
