Metadata-Version: 2.1
Name: codeElfin
Version: 0.0.2
Summary: 常用功能模块快速使用库.
Classifier: Programming Language :: Python :: 3
Classifier: License :: OSI Approved :: Apache Software License
Requires-Python: >=3.9
License-File: LICENSE
Requires-Dist: loguru>=0.7.2
